nonebot_plugin_yuanshen_notice/__init__.py
nonebot_plugin_yuanshen_notice-0.1.7.dist-info/LICENSE
nonebot_plugin_yuanshen_notice-0.1.7.dist-info/METADATA
nonebot_plugin_yuanshen_notice-0.1.7.dist-info/WHEEL
nonebot_plugin_yuanshen_notice-0.1.7.dist-info/RECORD
