Metadata-Version: 2.1
Name: nonebot-plugin-yuanshen-notice
Version: 0.1.7
Summary: 一个基于nonebot实现原神公告实时展示的插件
License: MIT
Author: mengxinyuan
Author-email: 1648576390@qq.com
Requires-Python: >=3.8,<4.0
Classifier: License :: OSI Approved :: MIT License
Classifier: Programming Language :: Python :: 3
Classifier: Programming Language :: Python :: 3.8
Classifier: Programming Language :: Python :: 3.9
Classifier: Programming Language :: Python :: 3.10
Classifier: Programming Language :: Python :: 3.11
Requires-Dist: httpx (>=0.23.0,<0.24.0)
Requires-Dist: nonebot-adapter-onebot (>=2.1.5,<3.0.0)
Requires-Dist: nonebot2 (>=2.0.0rc1,<3.0.0)
